odoo/addons/l10n_be_partner_kbo_bce/README.rst
odoo/addons/l10n_be_partner_kbo_bce/__init__.py
odoo/addons/l10n_be_partner_kbo_bce/__manifest__.py
odoo/addons/l10n_be_partner_kbo_bce/data/res_partner_id_category.xml
odoo/addons/l10n_be_partner_kbo_bce/demo/res_partner.xml
odoo/addons/l10n_be_partner_kbo_bce/i18n/fr.po
odoo/addons/l10n_be_partner_kbo_bce/i18n/l10n_be_partner_kbo_bce.pot
odoo/addons/l10n_be_partner_kbo_bce/i18n/nl.po
odoo/addons/l10n_be_partner_kbo_bce/models/__init__.py
odoo/addons/l10n_be_partner_kbo_bce/models/res_partner.py
odoo/addons/l10n_be_partner_kbo_bce/models/res_partner_id_category.py
odoo/addons/l10n_be_partner_kbo_bce/readme/CONTRIBUTORS.rst
odoo/addons/l10n_be_partner_kbo_bce/readme/DESCRIPTION.rst
odoo/addons/l10n_be_partner_kbo_bce/readme/INSTALL.rst
odoo/addons/l10n_be_partner_kbo_bce/static/description/icon.png
odoo/addons/l10n_be_partner_kbo_bce/static/description/index.html
odoo/addons/l10n_be_partner_kbo_bce/tests/__init__.py
odoo/addons/l10n_be_partner_kbo_bce/tests/test_l10n_be_partner_kbo_bce.py
odoo/addons/l10n_be_partner_kbo_bce/views/res_partner.xml
odoo13_addon_l10n_be_partner_kbo_bce-13.0.1.0.2.dist-info/METADATA
odoo13_addon_l10n_be_partner_kbo_bce-13.0.1.0.2.dist-info/WHEEL
odoo13_addon_l10n_be_partner_kbo_bce-13.0.1.0.2.dist-info/top_level.txt
odoo13_addon_l10n_be_partner_kbo_bce-13.0.1.0.2.dist-info/RECORD
